tardis_client/__init__.py
tardis_client/channel.py
tardis_client/consts.py
tardis_client/data_downloader.py
tardis_client/handy.py
tardis_client/reconstructors/__init__.py
tardis_client/reconstructors/bitmex.py
tardis_client/reconstructors/market_reconstructor.py
tardis_client/tardis_client.py
tardis_client-1.3.10.dist-info/LICENSE
tardis_client-1.3.10.dist-info/WHEEL
tardis_client-1.3.10.dist-info/METADATA
tardis_client-1.3.10.dist-info/RECORD
