Metadata-Version: 2.1
Name: tardis-client
Version: 1.3.10
Summary: Python client for tardis.dev - historical tick-level cryptocurrency market data replay API.
Home-page: https://github.com/tardis-dev/python-client
License: MPL-2.0
Keywords: cryptocurrency data feed,market data,api client,orderbook,crypto markets data replay,historical data,historical cryptocurrency prices,cryptocurrency api
Author: Thad
Author-email: thad@tardis.dev
Requires-Python: >=3.8,<4.0
Classifier: License :: OSI Approved
Classifier: Programming Language :: Python :: 3
Classifier: Programming Language :: Python :: 3.8
Classifier: Programming Language :: Python :: 3.9
Classifier: Programming Language :: Python :: 3.10
Classifier: Programming Language :: Python :: 3.11
Requires-Dist: aiofiles (>=24.1.0,<25.0.0)
Requires-Dist: aiohttp (>=3.10.0)
Requires-Dist: sortedcontainers (>=2.1,<3.0)
